glowingbike/__init__.py
glowingbike/bike.py
glowingbike/functions/__init__.py
glowingbike/functions/driving_animation.py
glowingbike/functions/fadeout_animation.py
glowingbike/functions/turn_animation.py
glowingbike-1.0.10.dist-info/LICENSE
glowingbike-1.0.10.dist-info/METADATA
glowingbike-1.0.10.dist-info/WHEEL
glowingbike-1.0.10.dist-info/top_level.txt
glowingbike-1.0.10.dist-info/RECORD
