Metadata-Version: 2.1
Name: glowingbike
Version: 1.0.10
Summary: Upgrade your bike with LEDs, raibows and turn signals.
Home-page: https://github.com/glowingkitty/The-Glowing-Bike-Project
Author: Marco
License: UNKNOWN
Platform: UNKNOWN
Classifier: Programming Language :: Python :: 3
Classifier: License :: OSI Approved :: MIT License
Classifier: Operating System :: OS Independent
Requires-Python: >=3.6
Requires-Dist: neopixel-plus
Requires-Dist: keyboard
